
{
    "clients": {
        "Gexp": {
            "version": "1.8.12-stable",
            "platforms": {
                "linux": {
                    "x64": {
                        "download": {
                            "url": "http://build.expanse.tech/release/latest/gexp-linux-amd64.tar.gz",
                            "type": "tar",
                            "md5": "f562e67c32ad7c5689400094a9c8c3d1",
                            "bin": "gexp-linux-amd64/gexp"
                        },
                        "bin": "gexp",
                        "commands": {
                            "sanity": {
                                "args": ["version"],
                                "output": [ "Gexp", "1.8.12-stable" ]
                            }
                        }
                    },
                    "ia32": {
                        "download": {
                            "url": "http://build.expanse.tech/release/latest/gexp-linux-386.tar.gz",
                            "type": "tar",
                            "md5": "03338f1d66df85d643227a3d7d51ca79",
                            "bin": "gexp-linux-386/gexp"
                        },
                        "bin": "gexp",
                        "commands": {
                            "sanity": {
                                "args": ["version"],
                                "output": [ "Gexp", "1.8.12-stable" ]
                            }
                        }
                    }
                },
                "mac": {
                    "x64": {
                        "download": {
                            "url": "http://build.expanse.tech/release/latest/gexp-darwin-amd64.tar.gz",
                            "type": "tar",
                            "md5": "edff86ddd558aad631fa347348fbdcd7",
                            "bin": "gexp-darwin-amd64/gexp"
                        },
                        "bin": "gexp",
                        "commands": {
                            "sanity": {
                                "args": ["version"],
                                "output": [ "Gexp", "1.8.12-stable" ]
                            }
                        }
                    }
                },
                "win": {
                    "x64": {
                        "download": {
                            "url": "http://build.expanse.tech/release/latest/gexp-windows-amd64.zip",
                            "type": "zip",
                            "md5": "141a2050ffb32441905129549ec889a2",
                            "bin": "gexp-windows-amd64\\gexp.exe"
                        },
                        "bin": "gexp.exe",
                        "commands": {
                            "sanity": {
                                "args": ["version"],
                                "output": [ "Gexp", "1.8.12-stable" ]
                            }
                        }
                    },
                    "ia32": {
                        "download": {
                            "url": "http://build.expanse.tech/release/latest/gexp-windows-386.zip",
                            "type": "zip",
                            "md5": "fbcf1ae8ab638c1be1e989370c7fbc84",
                            "bin": "gexp-windows-386\\gexp.exe"
                        },
                        "bin": "gexp.exe",
                        "commands": {
                            "sanity": {
                                "args": ["version"],
                                "output": [ "Gexp", "1.8.12-stable" ]
                            }
                        }
                    }
                }
            }
        }
    }
}
